{"name":"build-javascript","namedChunkGroups":{"polyfill":{"name":"polyfill","assets":[{"name":"webpack-runtime-7f6a74a94e42d0452a46.js","size":5316},{"name":"polyfill-be056948c8203b0b23af.js","size":98207}],"filteredAssets":0,"assetsSize":103523,"filteredAuxiliaryAssets":0,"auxiliaryAssetsSize":0},"app":{"name":"app","assets":[{"name":"webpack-runtime-7f6a74a94e42d0452a46.js","size":5316},{"name":"styles.5dc9a7035ef1af95b238.css","size":11040},{"name":"framework-872d99891669235e33e1.js","size":140716},{"name":"app-391d003730e6dcb0e25e.js","size":71103}],"filteredAssets":0,"assetsSize":228175,"filteredAuxiliaryAssets":36,"auxiliaryAssetsSize":677124},"component---src-pages-404-js":{"name":"component---src-pages-404-js","assets":[{"name":"styles.5dc9a7035ef1af95b238.css","size":11040},{"name":"commons-840cac3afd800869c141.js","size":37408},{"name":"component---src-pages-404-js-d521a1d7f6bb8fac3c4f.js","size":804}],"filteredAssets":0,"assetsSize":49252,"filteredAuxiliaryAssets":36,"auxiliaryAssetsSize":677124},"component---src-pages-datenschutz-js":{"name":"component---src-pages-datenschutz-js","assets":[{"name":"styles.5dc9a7035ef1af95b238.css","size":11040},{"name":"commons-840cac3afd800869c141.js","size":37408},{"name":"component---src-pages-datenschutz-js-11335ea6daa74bcb7009.js","size":32289}],"filteredAssets":0,"assetsSize":80737,"filteredAuxiliaryAssets":36,"auxiliaryAssetsSize":677124},"component---src-pages-djangogirls-js":{"name":"component---src-pages-djangogirls-js","assets":[{"name":"styles.5dc9a7035ef1af95b238.css","size":11040},{"name":"commons-840cac3afd800869c141.js","size":37408},{"name":"61578344b2198d4d111d6a1f5e60d71cf878631c-298a1c31c8e7f63c5717.js","size":11055},{"name":"component---src-pages-djangogirls-js-cadd5f839ea982797dc6.js","size":3101}],"filteredAssets":0,"assetsSize":62604,"filteredAuxiliaryAssets":36,"auxiliaryAssetsSize":677124},"component---src-pages-hilfe-js":{"name":"component---src-pages-hilfe-js","assets":[{"name":"styles.5dc9a7035ef1af95b238.css","size":11040},{"name":"commons-840cac3afd800869c141.js","size":37408},{"name":"component---src-pages-hilfe-js-69a2e8cd8eb4713cd227.js","size":2911}],"filteredAssets":0,"assetsSize":51359,"filteredAuxiliaryAssets":36,"auxiliaryAssetsSize":677124},"component---src-pages-index-js":{"name":"component---src-pages-index-js","assets":[{"name":"styles.5dc9a7035ef1af95b238.css","size":11040},{"name":"commons-840cac3afd800869c141.js","size":37408},{"name":"61578344b2198d4d111d6a1f5e60d71cf878631c-298a1c31c8e7f63c5717.js","size":11055},{"name":"component---src-pages-index-js-9543e4fca12d0f3bc385.js","size":2825}],"filteredAssets":0,"assetsSize":62328,"filteredAuxiliaryAssets":36,"auxiliaryAssetsSize":677124},"component---src-pages-slack-js":{"name":"component---src-pages-slack-js","assets":[{"name":"styles.5dc9a7035ef1af95b238.css","size":11040},{"name":"commons-840cac3afd800869c141.js","size":37408},{"name":"component---src-pages-slack-js-d6b33d89a76415fb1cdf.js","size":1002}],"filteredAssets":0,"assetsSize":49450,"filteredAuxiliaryAssets":36,"auxiliaryAssetsSize":677124},"component---src-pages-termine-js":{"name":"component---src-pages-termine-js","assets":[{"name":"styles.5dc9a7035ef1af95b238.css","size":11040},{"name":"commons-840cac3afd800869c141.js","size":37408},{"name":"component---src-pages-termine-js-a9ae457e8bf63df5a67d.js","size":3485}],"filteredAssets":0,"assetsSize":51933,"filteredAuxiliaryAssets":36,"auxiliaryAssetsSize":677124},"component---src-pages-verein-js":{"name":"component---src-pages-verein-js","assets":[{"name":"styles.5dc9a7035ef1af95b238.css","size":11040},{"name":"commons-840cac3afd800869c141.js","size":37408},{"name":"component---src-pages-verein-js-8842ef02bcfeeb48b7b7.js","size":2978}],"filteredAssets":0,"assetsSize":51426,"filteredAuxiliaryAssets":36,"auxiliaryAssetsSize":677124}},"assetsByChunkName":{"polyfill":["webpack-runtime-7f6a74a94e42d0452a46.js","polyfill-be056948c8203b0b23af.js"],"app":["webpack-runtime-7f6a74a94e42d0452a46.js","styles.5dc9a7035ef1af95b238.css","framework-872d99891669235e33e1.js","app-391d003730e6dcb0e25e.js"],"component---src-pages-404-js":["styles.5dc9a7035ef1af95b238.css","commons-840cac3afd800869c141.js","component---src-pages-404-js-d521a1d7f6bb8fac3c4f.js"],"component---src-pages-datenschutz-js":["styles.5dc9a7035ef1af95b238.css","commons-840cac3afd800869c141.js","component---src-pages-datenschutz-js-11335ea6daa74bcb7009.js"],"component---src-pages-djangogirls-js":["styles.5dc9a7035ef1af95b238.css","commons-840cac3afd800869c141.js","61578344b2198d4d111d6a1f5e60d71cf878631c-298a1c31c8e7f63c5717.js","component---src-pages-djangogirls-js-cadd5f839ea982797dc6.js"],"component---src-pages-hilfe-js":["styles.5dc9a7035ef1af95b238.css","commons-840cac3afd800869c141.js","component---src-pages-hilfe-js-69a2e8cd8eb4713cd227.js"],"component---src-pages-index-js":["styles.5dc9a7035ef1af95b238.css","commons-840cac3afd800869c141.js","61578344b2198d4d111d6a1f5e60d71cf878631c-298a1c31c8e7f63c5717.js","component---src-pages-index-js-9543e4fca12d0f3bc385.js"],"component---src-pages-slack-js":["styles.5dc9a7035ef1af95b238.css","commons-840cac3afd800869c141.js","component---src-pages-slack-js-d6b33d89a76415fb1cdf.js"],"component---src-pages-termine-js":["styles.5dc9a7035ef1af95b238.css","commons-840cac3afd800869c141.js","component---src-pages-termine-js-a9ae457e8bf63df5a67d.js"],"component---src-pages-verein-js":["styles.5dc9a7035ef1af95b238.css","commons-840cac3afd800869c141.js","component---src-pages-verein-js-8842ef02bcfeeb48b7b7.js"]},"childAssetsByChunkName":{}}